securityratconnector/__init__.py
securityratconnector/securityratconnector.py
securityratconnector-1.1.0.dist-info/LICENSE
securityratconnector-1.1.0.dist-info/WHEEL
securityratconnector-1.1.0.dist-info/METADATA
securityratconnector-1.1.0.dist-info/RECORD
