Metadata-Version: 2.1
Name: securityratconnector
Version: 1.1.0
Summary: An API connector for SecurityRat
Home-page: https://github.com/dcfSec/SecurityRatConnector
License: Apache-2.0
Author: dcfSec
Author-email: contributor@dcfsec.com
Requires-Python: >=3.6,<4.0
Classifier: License :: OSI Approved :: Apache Software License
Classifier: Programming Language :: Python :: 3
Classifier: Programming Language :: Python :: 3.10
Classifier: Programming Language :: Python :: 3.6
Classifier: Programming Language :: Python :: 3.7
Classifier: Programming Language :: Python :: 3.8
Classifier: Programming Language :: Python :: 3.9
Requires-Dist: requests (>=2.23.0,<3.0.0)
Project-URL: Repository, https://github.com/dcfSec/SecurityRatConnector
